apilibrary/__init__.py
apilibrary/team_org_chart_api.py
apilibrary/version.py
apilibrary/models/__init__.py
apilibrary/models/chart_data_view.py
apilibrary/models/chart_data_view_py3.py
apilibrary/models/chart_definition.py
apilibrary/models/chart_definition_py3.py
apilibrary/models/chart_layout_view_model.py
apilibrary/models/chart_layout_view_model_py3.py
apilibrary/models/chart_node.py
apilibrary/models/chart_node_py3.py
apilibrary/models/chart_position.py
apilibrary/models/chart_position_py3.py
apilibrary/models/create_chart_model.py
apilibrary/models/create_chart_model_py3.py
apilibrary/models/json_chart_item_view_model.py
apilibrary/models/json_chart_item_view_model_py3.py
apilibrary/models/remapping.py
apilibrary/models/remapping_py3.py
apilibrary/models/vacant_position_view_model.py
apilibrary/models/vacant_position_view_model_py3.py
apilibrary/operations/__init__.py
apilibrary/operations/chart_data_api_operations.py
apilibrary/operations/charts_api_operations.py
apilibrary/operations/positions_api_operations.py
apilibrary/operations/remappings_api_operations.py
tocapilibrarypython-1.0.0.dist-info/LICENSE
tocapilibrarypython-1.0.0.dist-info/METADATA
tocapilibrarypython-1.0.0.dist-info/WHEEL
tocapilibrarypython-1.0.0.dist-info/top_level.txt
tocapilibrarypython-1.0.0.dist-info/RECORD
