Metadata-Version: 2.1
Name: tocapilibrarypython
Version: 1.0.0
Summary: TeamOrgChart API Python Library
Home-page: https://github.com/TeamOrgChart/tocapilibrarypython
Author: TeamImprover
Author-email: vlad@devmiles.com
License: UNKNOWN
Platform: UNKNOWN
Classifier: Programming Language :: Python :: 3
Classifier: License :: OSI Approved :: MIT License
Classifier: Operating System :: OS Independent
Requires-Python: >=3.4
